djiiif/__init__.py
djiiif/templatetags/__init__.py
djiiif/templatetags/iiiftags.py
djiiif-0.20.dist-info/LICENSE.txt
djiiif-0.20.dist-info/METADATA
djiiif-0.20.dist-info/WHEEL
djiiif-0.20.dist-info/top_level.txt
djiiif-0.20.dist-info/RECORD
